spear_ai_sqlfluff_config/.sqlfluff
spear_ai_sqlfluff_config/__init__.py
spear_ai_sqlfluff_config-2.0.2.dist-info/METADATA
spear_ai_sqlfluff_config-2.0.2.dist-info/WHEEL
spear_ai_sqlfluff_config-2.0.2.dist-info/RECORD
